cupcake/__init__.py
cupcake/cascade.py
cupcake/confee.py
cupcake/data/cmake_names.py
cupcake/data/new/.gitignore
cupcake/data/new/CMakeLists.txt
cupcake/data/new/conanfile.py
cupcake/data/new/include/{{name}}/{{name}}.hpp
cupcake/data/new/src/lib{{name}}.cpp
cupcake/data/new/src/{{name}}.cpp
cupcake/data/new/tests/CMakeLists.txt
cupcake/data/new/tests/{{name}}.cpp
cupcake/data/query/CMakeLists.txt
cupcake/expression.py
cupcake/functional.py
cupcake/main.py
cupcake/transformations.py
cupcake-1.2.2.dist-info/LICENSE
cupcake-1.2.2.dist-info/METADATA
cupcake-1.2.2.dist-info/WHEEL
cupcake-1.2.2.dist-info/entry_points.txt
cupcake-1.2.2.dist-info/RECORD
