Metadata-Version: 2.1
Name: cupcake
Version: 1.2.2
Summary: Make C++ a piece of cake.
Author: John Freeman
Author-email: jfreeman08@gmail.com
Requires-Python: >=3.9,<4.0
Classifier: Programming Language :: Python :: 3
Classifier: Programming Language :: Python :: 3.9
Classifier: Programming Language :: Python :: 3.10
Classifier: Programming Language :: Python :: 3.11
Classifier: Programming Language :: Python :: 3.12
Requires-Dist: click (>=8.0.4,<9.0.0)
Requires-Dist: click-option-group (>=0.5.3,<0.6.0)
Requires-Dist: jinja2 (>=3.1.1,<4.0.0)
Requires-Dist: psutil (>=5.9.8,<6.0.0)
Requires-Dist: semver (>=3.0.2,<4.0.0)
Requires-Dist: tomlkit (>=0.10.1,<0.11.0)
